{
  "status": "SUCCEEDED",
  "message": "Success",
  "requestId": "1554045455@qtp-1945836927-145",
  "totalResults": 1,
  "fileList": [
    {
      "accessTime": 0,
      "blockSize": 0,
      "group": "hadoop",
      "length": 0,
      "modificationTime": 1495126774789,
      "owner": "yarn",
      "pathSuffix": "app-logs",
      "permission": "rwxrwxrwx",
      "replication": 0,
      "type": "DIRECTORY"
    },
    {
      "accessTime": 0,
      "blockSize": 0,
      "group": "hdfs",
      "length": 0,
      "modificationTime": 1495126756753,
      "owner": "hdfs",
      "pathSuffix": "apps",
      "permission": "rwxr-xr-x",
      "replication": 0,
      "type": "DIRECTORY"
    },
    {
      "accessTime": 0,
      "blockSize": 0,
      "group": "hadoop",
      "length": 0,
      "modificationTime": 1495126617683,
      "owner": "yarn",
      "pathSuffix": "ats",
      "permission": "rwxr-xr-x",
      "replication": 0,
      "type": "DIRECTORY"
    },
    {
      "accessTime": 0,
      "blockSize": 0,
      "group": "hdfs",
      "length": 0,
      "modificationTime": 1495126625028,
      "owner": "hdfs",
      "pathSuffix": "hdp",
      "permission": "rwxr-xr-x",
      "replication": 0,
      "type": "DIRECTORY"
    },
    {
      "accessTime": 0,
      "blockSize": 0,
      "group": "hdfs",
      "length": 0,
      "modificationTime": 1495126621964,
      "owner": "mapred",
      "pathSuffix": "mapred",
      "permission": "rwxr-xr-x",
      "replication": 0,
      "type": "DIRECTORY"
    },
    {
      "accessTime": 0,
      "blockSize": 0,
      "group": "hadoop",
      "length": 0,
      "modificationTime": 1495126636614,
      "owner": "mapred",
      "pathSuffix": "mr-history",
      "permission": "rwxrwxrwx",
      "replication": 0,
      "type": "DIRECTORY"
    },
    {
      "accessTime": 0,
      "blockSize": 0,
      "group": "hdfs",
      "length": 0,
      "modificationTime": 1495126956208,
      "owner": "hdfs",
      "pathSuffix": "tmp",
      "permission": "rwxrwxrwx",
      "replication": 0,
      "type": "DIRECTORY"
    },
    {
      "accessTime": 0,
      "blockSize": 0,
      "group": "hdfs",
      "length": 0,
      "modificationTime": 1495126756899,
      "owner": "hdfs",
      "pathSuffix": "user",
      "permission": "rwxr-xr-x",
      "replication": 0,
      "type": "DIRECTORY"
    },
    {
      "accessTime": 0,
      "blockSize": 0,
      "group": "hdfs",
      "length": 0,
      "modificationTime": 1495126756899,
      "owner": "hdfs",
      "pathSuffix": "one",
      "permission": "rwxr-xr-x",
      "replication": 0,
      "type": "DIRECTORY"
    },
    {
      "accessTime": 0,
      "blockSize": 0,
      "group": "hdfs",
      "length": 0,
      "modificationTime": 1495126756899,
      "owner": "hdfs",
      "pathSuffix": "two",
      "permission": "rwxr-xr-x",
      "replication": 0,
      "type": "DIRECTORY"
    },
    {
      "accessTime": 0,
      "blockSize": 0,
      "group": "hdfs",
      "length": 0,
      "modificationTime": 1495126756899,
      "owner": "hdfs",
      "pathSuffix": "three",
      "permission": "rwxr-xr-x",
      "replication": 0,
      "type": "DIRECTORY"
    },
    {
      "accessTime": 0,
      "blockSize": 0,
      "group": "hdfs",
      "length": 0,
      "modificationTime": 1495126756899,
      "owner": "hdfs",
      "pathSuffix": "four",
      "permission": "rwxr-xr-x",
      "replication": 0,
      "type": "DIRECTORY"
    },
    {
      "accessTime": 0,
      "blockSize": 0,
      "group": "hdfs",
      "length": 0,
      "modificationTime": 1495126756899,
      "owner": "hdfs",
      "pathSuffix": "five",
      "permission": "rwxr-xr-x",
      "replication": 0,
      "type": "DIRECTORY"
    },
    {
      "accessTime": 0,
      "blockSize": 0,
      "group": "hdfs",
      "length": 0,
      "modificationTime": 1495126756899,
      "owner": "hdfs",
      "pathSuffix": "six",
      "permission": "rwxr-xr-x",
      "replication": 0,
      "type": "DIRECTORY"
    },
    {
      "accessTime": 0,
      "blockSize": 0,
      "group": "hdfs",
      "length": 0,
      "modificationTime": 1495126756899,
      "owner": "hdfs",
      "pathSuffix": "seven",
      "permission": "rwxr-xr-x",
      "replication": 0,
      "type": "DIRECTORY"
    }
  ]
}
